{"chunk_definitions":[{"row":6,"row_count":1,"visible":true,"expansion_state":0,"options":{"engine":"r","label":"unnamed-chunk-413"},"document_id":"74CCE2A4","chunk_id":"c6b0p9ufuxrdu","chunk_label":"unnamed-chunk-1"},{"row":27,"row_count":1,"visible":true,"expansion_state":0,"options":{"engine":"r","label":"unnamed-chunk-414"},"document_id":"74CCE2A4","chunk_id":"c7i1uocb5hdo8","chunk_label":"unnamed-chunk-2"},{"row":34,"row_count":1,"visible":true,"expansion_state":0,"options":{"engine":"r","label":"unnamed-chunk-415"},"document_id":"74CCE2A4","chunk_id":"czpysia39j9j1","chunk_label":"unnamed-chunk-3"},{"row":108,"row_count":1,"visible":true,"expansion_state":0,"options":{"engine":"r","label":"unnamed-chunk-416"},"document_id":"74CCE2A4","chunk_id":"cbgo80hfwhc3n","chunk_label":"unnamed-chunk-4"},{"row":123,"row_count":1,"visible":true,"expansion_state":0,"options":{"engine":"r","label":"unnamed-chunk-417"},"document_id":"74CCE2A4","chunk_id":"cfh4bn6d6qe3k","chunk_label":"unnamed-chunk-5"},{"row":129,"row_count":1,"visible":true,"expansion_state":0,"options":{"engine":"r","label":"unnamed-chunk-418"},"document_id":"74CCE2A4","chunk_id":"cs74e8g5yer5l","chunk_label":"unnamed-chunk-6"},{"row":135,"row_count":1,"visible":true,"expansion_state":0,"options":{"engine":"r","label":"unnamed-chunk-419"},"document_id":"74CCE2A4","chunk_id":"cv9ea07qhql1m","chunk_label":"unnamed-chunk-7"},{"row":140,"row_count":1,"visible":true,"expansion_state":0,"options":{"engine":"r","label":"unnamed-chunk-420"},"document_id":"74CCE2A4","chunk_id":"cqjkizfoe5gjj","chunk_label":"unnamed-chunk-8"},{"row":145,"row_count":1,"visible":true,"expansion_state":0,"options":{"engine":"r","label":"unnamed-chunk-421"},"document_id":"74CCE2A4","chunk_id":"cmb9rsvlhutz4","chunk_label":"unnamed-chunk-9"},{"row":157,"row_count":1,"visible":true,"expansion_state":0,"options":{"engine":"r","label":"unnamed-chunk-422"},"document_id":"74CCE2A4","chunk_id":"cr93iojpzw0l5","chunk_label":"unnamed-chunk-10"},{"row":169,"row_count":1,"visible":true,"expansion_state":0,"options":{"engine":"r","label":"unnamed-chunk-423"},"document_id":"74CCE2A4","chunk_id":"cdhnbfozw3tpt","chunk_label":"unnamed-chunk-11"},{"row":181,"row_count":1,"visible":true,"expansion_state":0,"options":{"engine":"r","label":"unnamed-chunk-424"},"document_id":"74CCE2A4","chunk_id":"ceo8huh39he5j","chunk_label":"unnamed-chunk-12"},{"row":212,"row_count":1,"visible":true,"expansion_state":0,"options":{"engine":"r","label":"unnamed-chunk-425"},"document_id":"74CCE2A4","chunk_id":"chj9shpjd0i2w","chunk_label":"unnamed-chunk-13"},{"row":227,"row_count":1,"visible":true,"expansion_state":0,"options":{"engine":"r","label":"unnamed-chunk-426"},"document_id":"74CCE2A4","chunk_id":"cs026xst8u62m","chunk_label":"unnamed-chunk-14"},{"row":236,"row_count":1,"visible":true,"expansion_state":0,"options":{"engine":"r","label":"unnamed-chunk-427"},"document_id":"74CCE2A4","chunk_id":"cqx4oa3fupb5z","chunk_label":"unnamed-chunk-15"},{"row":251,"row_count":1,"visible":true,"expansion_state":0,"options":{"engine":"r","label":"unnamed-chunk-428"},"document_id":"74CCE2A4","chunk_id":"c76kxqjdd4lix","chunk_label":"unnamed-chunk-16"},{"row":268,"row_count":1,"visible":true,"expansion_state":0,"options":{"engine":"r","label":"unnamed-chunk-429"},"document_id":"74CCE2A4","chunk_id":"csemb1q133we0","chunk_label":"unnamed-chunk-17"},{"row":275,"row_count":1,"visible":true,"expansion_state":0,"options":{"engine":"r","label":"unnamed-chunk-430"},"document_id":"74CCE2A4","chunk_id":"c5lyxicp60wd1","chunk_label":"unnamed-chunk-18"},{"row":282,"row_count":1,"visible":true,"expansion_state":0,"options":{"engine":"r","label":"unnamed-chunk-431"},"document_id":"74CCE2A4","chunk_id":"cn322j72750pm","chunk_label":"unnamed-chunk-19"},{"row":289,"row_count":1,"visible":true,"expansion_state":0,"options":{"engine":"r","label":"unnamed-chunk-432"},"document_id":"74CCE2A4","chunk_id":"c7slnqesbbmpd","chunk_label":"unnamed-chunk-20"},{"row":293,"row_count":1,"visible":true,"expansion_state":0,"options":{"engine":"r","label":"unnamed-chunk-433"},"document_id":"74CCE2A4","chunk_id":"ccb389o919e93","chunk_label":"unnamed-chunk-21"},{"row":304,"row_count":1,"visible":true,"expansion_state":0,"options":{"engine":"r","label":"unnamed-chunk-434"},"document_id":"74CCE2A4","chunk_id":"cs7isddatzufa","chunk_label":"unnamed-chunk-22"},{"row":311,"row_count":1,"visible":true,"expansion_state":0,"options":{"engine":"r","label":"unnamed-chunk-435"},"document_id":"74CCE2A4","chunk_id":"cuwis9em2i3o8","chunk_label":"unnamed-chunk-23"},{"row":318,"row_count":1,"visible":true,"expansion_state":0,"options":{"engine":"r","label":"unnamed-chunk-436"},"document_id":"74CCE2A4","chunk_id":"clz02k6woyz7n","chunk_label":"unnamed-chunk-24"},{"row":325,"row_count":1,"visible":true,"expansion_state":0,"options":{"engine":"r","label":"unnamed-chunk-437"},"document_id":"74CCE2A4","chunk_id":"ceuwmpy7jsgi4","chunk_label":"unnamed-chunk-25"},{"row":336,"row_count":1,"visible":true,"expansion_state":0,"options":{"engine":"r","label":"unnamed-chunk-438"},"document_id":"74CCE2A4","chunk_id":"c4zquz1yuozqy","chunk_label":"unnamed-chunk-26"},{"row":374,"row_count":1,"visible":true,"expansion_state":0,"options":{"engine":"r","label":"unnamed-chunk-441"},"document_id":"74CCE2A4","chunk_id":"c04kdc6t1y56n","chunk_label":"unnamed-chunk-27"},{"row":379,"row_count":1,"visible":true,"expansion_state":0,"options":{"engine":"r","label":"unnamed-chunk-442"},"document_id":"74CCE2A4","chunk_id":"cgax7enzaudvu","chunk_label":"unnamed-chunk-28"}],"doc_write_time":1700012985}